mafipy/__init__.py
mafipy/calibrator/__init__.py
mafipy/calibrator/implied_vol.py
mafipy/calibrator/sabr.py
mafipy/calibrator/tests/__init__.py
mafipy/calibrator/tests/test_implied_vol.py
mafipy/calibrator/tests/test_sabr.py
mafipy/calibrator/tests/util.py
mafipy/function/__init__.py
mafipy/function/analytic_formula.py
mafipy/function/black.py
mafipy/function/black_scholes.py
mafipy/function/error.py
mafipy/function/local_vol.py
mafipy/function/math_formula.py
mafipy/function/payoff.py
mafipy/function/sabr.py
mafipy/function/util.py
mafipy/function/tests/__init__.py
mafipy/function/tests/test_analytic_formula.py
mafipy/function/tests/test_black.py
mafipy/function/tests/test_black_scholes.py
mafipy/function/tests/test_local_vol.py
mafipy/function/tests/test_math_formula.py
mafipy/function/tests/test_payoff.py
mafipy/function/tests/test_sabr.py
mafipy/function/tests/util.py
mafipy/math/__init__.py
mafipy/math/qmc/__init__.py
mafipy/math/qmc/_sobol.cpython-38-darwin.so
mafipy/math/qmc/sobol.py
mafipy/math/qmc/tests/__init__.py
mafipy/math/qmc/tests/test_sobol.py
mafipy/replication/__init__.py
mafipy/replication/_quanto_cms_forward_fx.py
mafipy/replication/error.py
mafipy/replication/pricer_quanto_cms.py
mafipy/replication/replication_method.py
mafipy/replication/util.py
mafipy/replication/tests/__init__.py
mafipy/replication/tests/test__quanto_cms_forward_fx.py
mafipy/replication/tests/test_pricer_quanto_cms.py
mafipy/replication/tests/test_replication_method.py
mafipy/replication/tests/util.py
mafipy/util/__init__.py
mafipy/util/error.py
mafipy/util/util.py
mafipy/util/utils.py
mafipy-0.1.dev12.dist-info/LICENSE
mafipy-0.1.dev12.dist-info/METADATA
mafipy-0.1.dev12.dist-info/WHEEL
mafipy-0.1.dev12.dist-info/top_level.txt
mafipy-0.1.dev12.dist-info/RECORD
