Metadata-Version: 2.1
Name: mafipy
Version: 0.1.dev12
Summary: 
Home-page: UNKNOWN
Maintainer: i05nagai
Maintainer-email: 
License: UNKNOWN
Platform: UNKNOWN
Classifier: Development Status :: 1 - Planning
Classifier: Intended Audience :: Science/Research
Classifier: Intended Audience :: Developers
Classifier: Programming Language :: Python
Classifier: Programming Language :: Python :: 3.5
Classifier: Topic :: Software Development
Classifier: Topic :: Scientific/Engineering
Classifier: Operating System :: Unix
Classifier: Operating System :: MacOS
Requires-Dist: numpy (==1.21.0)
Requires-Dist: scipy (==1.10.0)
